README.md
setup.py
riskmodeler/IGN_UI.py
riskmodeler/__init__.py
riskmodeler/base.py
riskmodeler/func.py
riskmodeler/funcc.py
riskmodeler/inputdata.py
riskmodeler/interactive_grouping.py
riskmodeler/load_node.py
riskmodeler/model.py
riskmodeler/model_result_ui.py
riskmodeler/model_ui.py
riskmodeler/policy.py
riskmodeler/sampling.py
riskmodeler/score_result_ui.py
riskmodeler/score_ui.py
riskmodeler/split.py
riskmodeler/start.py
riskmodeler/test.py
riskmodeler/ttttt.py
riskmodeler/var_clus.py
riskmodeler.egg-info/PKG-INFO
riskmodeler.egg-info/SOURCES.txt
riskmodeler.egg-info/dependency_links.txt
riskmodeler.egg-info/not-zip-safe
riskmodeler.egg-info/requires.txt
riskmodeler.egg-info/top_level.txt