Metadata-Version: 1.2
Name: riskmodeler
Version: 2.2.2
Summary: scorecard build tool
Home-page: https://github.com/nothingyang/RiskModeler
Author: Yang xuewen
Author-email: yangxuewen1234@126.com
License: MIT
Platform: UNKNOWN
Requires-Python: >=3.6
